duckcli/AUTHORS
duckcli/__init__.py
duckcli/clibuffer.py
duckcli/clistyle.py
duckcli/clitoolbar.py
duckcli/compat.py
duckcli/completion_refresher.py
duckcli/config.py
duckcli/duckclirc
duckcli/key_bindings.py
duckcli/lexer.py
duckcli/main.py
duckcli/sqlcompleter.py
duckcli/sqlexecute.py
duckcli/packages/__init__.py
duckcli/packages/completion_engine.py
duckcli/packages/filepaths.py
duckcli/packages/parseutils.py
duckcli/packages/prompt_utils.py
duckcli/packages/special/__init__.py
duckcli/packages/special/dbcommands.py
duckcli/packages/special/favoritequeries.py
duckcli/packages/special/iocommands.py
duckcli/packages/special/main.py
duckcli/packages/special/utils.py
duckcli-0.2.1.dist-info/LICENSE
duckcli-0.2.1.dist-info/METADATA
duckcli-0.2.1.dist-info/WHEEL
duckcli-0.2.1.dist-info/entry_points.txt
duckcli-0.2.1.dist-info/top_level.txt
duckcli-0.2.1.dist-info/RECORD
